{
  "users": [
    {
      "id": 504,
      "customerName": "Ta Hong Duc",
      "customerPass": "csa",
      "customerAddress": "Truoc ngo",
      "customerSex": "Male",
      "customerEmail": "tahongduc01@gmail.com",
      "customerPhoneNumber": "0911799629",
      "customerIsAdmin": "True"
    },
    {
      "id": 1501,
      "customerName": "Ta Hong Duc",
      "customerPass": "csa",
      "customerAddress": "Truoc ngo",
      "customerSex": "Male",
      "customerEmail": "tahongduc01@gmail.com",
      "customerPhoneNumber": "0911799629",
      "customerIsAdmin": "False"
    },
    {
      "email": "tahongduc01@gmail.com",
      "password": "$2a$10$rQjNWi4Qz.PWx4jdul8JueFYVtcMeQGdtas3LZjhXt3V75R5j0IX.",
      "name": "Tạ Hồng Đức",
      "address": "Nghệ An",
      "sex": "male",
      "isAdmin": true,
      "phoneNumber": "0955651313",
      "id": 1502
    }
  ],
  "customer": [
    {
      "id": "146",
      "name": "Nguyễn Văn C",
      "pass": "123456",
      "address": "Nghệ An",
      "Email": "nguyenvanc@gmail.com",
      "phoneNumber": "0123457789"
    },
    {
      "id": "245",
      "name": "Nguyễn Thị D",
      "pass": "123456",
      "address": "Nghệ An",
      "Email": "nguyenthid@gmail.com",
      "phoneNumber": "0955655313"
    },
    {
      "email": "tahongduc01@gmail.com",
      "password": "123456",
      "name": "Tạ Hồng Đức",
      "address": "Nghệ An",
      "sex": "male",
      "isAdmin": true,
      "phoneNumber": "0955651313",
      "id": "cO0TKPt"
    },
    {
      "email": "tahongduc01@gmail.com",
      "password": "123456",
      "name": "Tạ Hồng Đức",
      "address": "Nghệ An",
      "sex": "male",
      "isAdmin": true,
      "phoneNumber": "0955651313",
      "id": "RXQTeJj"
    }
  ],
  "products": [
    {
      "id": 851,
      "name": "ads45y",
      "type": "Shirt",
      "quantity": "213",
      "dateAdded": "2023-03-01",
      "dateOfSale": "2023-02-17"
    },
    {
      "id": 1079,
      "name": "21",
      "type": "Shirt",
      "quantity": "18",
      "dateAdded": "2023-03-02",
      "dateOfSale": "2023-02-03"
    },
    {
      "id": 468,
      "name": "Ta Hong Duc",
      "type": "Shirt",
      "quantity": "36",
      "dateAdded": "2023-02-25",
      "dateOfSale": "2023-03-01"
    },
    {
      "id": 1609,
      "name": "sadasd",
      "type": "Shirt",
      "quantity": "30",
      "dateAdded": "2023-02-12",
      "dateOfSale": "2023-03-04"
    },
    {
      "id": 1990,
      "name": "jggggggg",
      "type": "Shirt",
      "quantity": "878",
      "dateAdded": "2023-02-22",
      "dateOfSale": "2023-02-28"
    }
  ],
  "selling": [
    {
      "id": 167,
      "name": "Ta Hong Duc1",
      "type": "Shirt",
      "quantity": "66",
      "price": "1",
      "dateOfSale": "2023-02-05"
    }
  ]
}